[{"id":1,"date_of_match":"2025-01-22","result":"2:1","team_1_id":4,"team_2_id":5,"tournament_id":1},{"id":2,"date_of_match":"2025-01-22","result":"2:3","team_1_id":4,"team_2_id":8,"tournament_id":1},{"id":3,"date_of_match":"2025-01-22","result":"2:1","team_1_id":4,"team_2_id":9,"tournament_id":1},{"id":4,"date_of_match":"2025-01-22","result":"0:3","team_1_id":5,"team_2_id":8,"tournament_id":1},{"id":5,"date_of_match":"2025-01-22","result":"4:4","team_1_id":5,"team_2_id":9,"tournament_id":1},{"id":6,"date_of_match":"2025-01-22","result":"1:3","team_1_id":8,"team_2_id":9,"tournament_id":1}]